[{"candidate_full_name": "Isabella Xi", "employee_login": "awsisabella", "internal_job_title": "ProServ", "": "", "cost_center": "5847", "state": "CO", "city": "Denver", "building": "DEN16", "keyword": ["TECHU", "CARVAJAL", "AWSJENE", "CARLOSM", "ECTSUMMER2021INTERNCONVERSION"], "mng_confirmed": "TRUE"}, {"candidate_full_name": "Camila Silva", "employee_login": "silvacam", "internal_job_title": "ProServ", "": "", "cost_center": "4075", "state": "WA", "city": "Seattle", "building": "SEA42", "keyword": ["TECHU", "BTAPTICH", "MOEAB", "RAMGOPA", "ECTSUMMER2021INTERNCONVERSION"], "mng_confirmed": "FALSE"}, {"candidate_full_name": "David Barnes", "employee_login": "barndavid", "internal_job_title": "ProServ", "": "", "cost_center": "5847", "state": "WA", "city": "Seattle", "building": "SEA42", "keyword": ["TECHU", "LOROCA", "GBROWN", "AWSPABLO", "ECTSUMMER2021INTERNCONVERSION"], "mng_confirmed": "TRUE"}, {"candidate_full_name": "Eva Rivera", "employee_login": "riveraeva", "internal_job_title": "ProServ", "": "", "cost_center": "4075", "state": "NY", "city": "New York", "building": "JFK14", "keyword": ["TECHU", "OSCARCAS", "MOHAMMADE", "CARLARIES", "ECTSUMMER2021INTERNCONVERSION"], "mng_confirmed": "TRUE"}]