[{"candidate_full_name": "Abigail Mejia", "employee_login": "mejiaabig", "internal_job_title": "Assoc customer solution Manager", "": "", "cost_center": "4442", "state": "NY", "city": "New York", "building": "JFK14", "keyword": ["TECHU", "LOROCA", "GBROWN", "AWSPABLO", "ECTSUMMER2021INTERNCONVERSION"], "mng_confirmed": "TRUE"}, {"candidate_full_name": "Abigail Mejia", "employee_login": "mejiaabig", "internal_job_title": "Assoc customer solution Manager", "": "", "cost_center": "4442", "state": "NY", "city": "New York", "building": "JFK14", "keyword": ["TECHU", "LOROCA", "GBROWN", "AWSPABLO", "ECTSUMMER2021INTERNCONVERSION"], "mng_confirmed": "TRUE"}, {"candidate_full_name": "Abigail Mejia", "employee_login": "mejiaabig", "internal_job_title": "Assoc customer solution Manager", "": "", "cost_center": "4442", "state": "NY", "city": "New York", "building": "JFK14", "keyword": ["TECHU", "LOROCA", "GBROWN", "AWSPABLO", "ECTSUMMER2021INTERNCONVERSION"], "mng_confirmed": "TRUE"}, {"candidate_full_name": "Abigail Mejia", "employee_login": "mejiaabig", "internal_job_title": "Assoc customer solution Manager", "": "", "cost_center": "4442", "state": "NY", "city": "New York", "building": "JFK14", "keyword": ["TECHU", "LOROCA", "GBROWN", "AWSPABLO", "ECTSUMMER2021INTERNCONVERSION"], "mng_confirmed": "TRUE"}, {"candidate_full_name": "Abigail Mejia", "employee_login": "mejiaabig", "internal_job_title": "Assoc customer solution Manager", "": "", "cost_center": "4442", "state": "NY", "city": "New York", "building": "JFK14", "keyword": ["TECHU", "LOROCA", "GBROWN", "AWSPABLO", "ECTSUMMER2021INTERNCONVERSION"], "mng_confirmed": "TRUE"}, {"candidate_full_name": "Abigail Mejia", "employee_login": "mejiaabig", "internal_job_title": "Assoc customer solution Manager", "": "", "cost_center": "4442", "state": "NY", "city": "New York", "building": "JFK14", "keyword": ["TECHU", "LOROCA", "GBROWN", "AWSPABLO", "ECTSUMMER2021INTERNCONVERSION"], "mng_confirmed": "TRUE"}, {"candidate_full_name": "Abigail Mejia", "employee_login": "mejiaabig", "internal_job_title": "Assoc customer solution Manager", "": "", "cost_center": "4442", "state": "NY", "city": "New York", "building": "JFK14", "keyword": ["TECHU", "LOROCA", "GBROWN", "AWSPABLO", "ECTSUMMER2021INTERNCONVERSION"], "mng_confirmed": "TRUE"}]